{"cameraMode":{"drawMode":0,"name":"Shaded","section":"Shading Mode"},"sceneLighting":true,"audioPlay":false,"sceneViewState":{"m_AlwaysRefresh":false,"showFog":true,"showSkybox":true,"showFlares":true,"showImageEffects":true,"showParticleSystems":true,"showVisualEffectGraphs":true,"m_FxEnabled":true},"in2DMode":false,"pivot":{"x":-11.269491195678711,"y":2.294870376586914,"z":-10.040237426757813},"rotation":{"x":0.008161555975675583,"y":0.7854911684989929,"z":0.010361499153077603,"w":-0.6187355518341065},"size":10.0,"orthographic":false}